[
  {"color":-16776961,"name":"Groceries"},
  {"color":-16751516,"name":"Drinks"},
  {"color":-12074644,"name":"Personal Care"},
  {"color":-16759452,"name":"Entertainment"},
  {"color":-39836,"name":"Games"},
  {"color":-39934,"name":"Car Expenses"},
  {"color":-5086108,"name":"Gifts"},
  {"color":-9240642,"name":"Parking"},
  {"color":-17920,"name":"Gas"},
  {"color":-4587520,"name":"Dining"},
  {"color":-12997874,"name":"Fees"},
  {"color":-12513692,"name":"Travel"},
  {"color":-11796481,"name":"Education"},
  {"color":-16711936,"name":"Bills"},
  {"color":-16769537,"name":"Debt"},
  {"color":-256,"name":"Rent"},
  {"color":-65236,"name":"Phone"},
  {"color":-65336,"name":"Insurance"}
]